gripql/__init__.py
gripql/aggregations.py
gripql/connection.py
gripql/graph.py
gripql/operators.py
gripql/query.py
gripql/util.py
gripql-0.8.0.dist-info/METADATA
gripql-0.8.0.dist-info/WHEEL
gripql-0.8.0.dist-info/top_level.txt
gripql-0.8.0.dist-info/zip-safe
gripql-0.8.0.dist-info/RECORD
